tpdk/__init__.py
tpdk/api_client.py
tpdk/api_response.py
tpdk/configuration.py
tpdk/exceptions.py
tpdk/py.typed
tpdk/rest.py
tpdk/api/__init__.py
tpdk/api/branding_api.py
tpdk/api/notification_api.py
tpdk/api/organization_api.py
tpdk/api/persona_api.py
tpdk/api/resolution_center_api.py
tpdk/api/user_api.py
tpdk/api/webhook_api.py
tpdk/models/__init__.py
tpdk/models/access_error.py
tpdk/models/address.py
tpdk/models/api_client_post_creation_read.py
tpdk/models/api_client_read.py
tpdk/models/api_client_write.py
tpdk/models/auth_error.py
tpdk/models/dispute_address_independent_write.py
tpdk/models/dispute_collection_read.py
tpdk/models/dispute_dispute_read.py
tpdk/models/dispute_independent_write.py
tpdk/models/dispute_media_read.py
tpdk/models/dispute_metadata_independent_write.py
tpdk/models/dispute_metadata_read.py
tpdk/models/dispute_offer_collection_read.py
tpdk/models/dispute_offer_independent_write.py
tpdk/models/dispute_offer_read.py
tpdk/models/dispute_organization_read.py
tpdk/models/dispute_parcel_independent_write.py
tpdk/models/dispute_parcel_read.py
tpdk/models/dispute_persona_collection_read.py
tpdk/models/dispute_persona_independent_write.py
tpdk/models/dispute_persona_read.py
tpdk/models/dispute_post_creation_read.py
tpdk/models/dispute_read.py
tpdk/models/dispute_transaction_collection_read.py
tpdk/models/dispute_transaction_independent_write.py
tpdk/models/dispute_transaction_read.py
tpdk/models/dispute_update.py
tpdk/models/dispute_view_read.py
tpdk/models/dispute_workflow_event_read.py
tpdk/models/evaluation_read.py
tpdk/models/evaluation_write.py
tpdk/models/evidence.py
tpdk/models/evidence_media_read.py
tpdk/models/evidence_read.py
tpdk/models/evidence_write.py
tpdk/models/generic_error.py
tpdk/models/invalid_query_error.py
tpdk/models/media.py
tpdk/models/media_dispute_read.py
tpdk/models/media_read.py
tpdk/models/media_user_read.py
tpdk/models/message_error.py
tpdk/models/metadata.py
tpdk/models/metadata_dispute_read.py
tpdk-2.0.204.dist-info/METADATA
tpdk-2.0.204.dist-info/WHEEL
tpdk-2.0.204.dist-info/top_level.txt
tpdk-2.0.204.dist-info/RECORD
