Metadata-Version: 2.1
Name: tpdk
Version: 2.0.204
Summary: Tripartie
Home-page: https://pypi.org/project/tpdk
Author: Tripartie SAS
Author-email: noc@tripartie.com
Keywords: OpenAPI,OpenAPI-Generator,Tripartie
Requires-Dist: urllib3 <2.1.0,>=1.25.3
Requires-Dist: python-dateutil
Requires-Dist: pydantic >=2
Requires-Dist: typing-extensions >=4.7.1
